README.md
setup.py
lamda/__init__.py
lamda/client.py
lamda/const.py
lamda/exceptions.py
lamda/types.py
lamda.egg-info/PKG-INFO
lamda.egg-info/SOURCES.txt
lamda.egg-info/dependency_links.txt
lamda.egg-info/not-zip-safe
lamda.egg-info/requires.txt
lamda.egg-info/top_level.txt
lamda/google/protobuf/any.proto
lamda/google/protobuf/api.proto
lamda/google/protobuf/descriptor.proto
lamda/google/protobuf/duration.proto
lamda/google/protobuf/empty.proto
lamda/google/protobuf/field_mask.proto
lamda/google/protobuf/source_context.proto
lamda/google/protobuf/struct.proto
lamda/google/protobuf/timestamp.proto
lamda/google/protobuf/type.proto
lamda/google/protobuf/wrappers.proto
lamda/google/protobuf/compiler/plugin.proto
lamda/rpc/application.proto
lamda/rpc/debug.proto
lamda/rpc/file.proto
lamda/rpc/policy.proto
lamda/rpc/proxy.proto
lamda/rpc/services.proto
lamda/rpc/settings.proto
lamda/rpc/shell.proto
lamda/rpc/status.proto
lamda/rpc/storage.proto
lamda/rpc/types.proto
lamda/rpc/uiautomator.proto
lamda/rpc/util.proto
lamda/rpc/wifi.proto