Metadata-Version: 2.4
Name: lamda
Version: 9.2
Summary: Android reverse engineering & automation framework (Client API)
Home-page: https://github.com/firerpa/lamda
Author: rev1si0n
Classifier: Environment :: Console
Classifier: Intended Audience :: Developers
Classifier: Development Status :: 5 - Production/Stable
Classifier: Intended Audience :: Information Technology
Classifier: Intended Audience :: Science/Research
Classifier: Programming Language :: Python :: 3
Classifier: Operating System :: Android
Classifier: Topic :: Security
Requires-Python: >=3.6,<3.14
Requires-Dist: grpcio-tools<=1.74.0,>=1.35.0
Requires-Dist: grpc-interceptor<=0.15.4,>=0.13.0
Requires-Dist: grpcio<=1.74.0,>=1.35.0
Requires-Dist: cryptography>=35.0.0
Requires-Dist: msgpack>=1.0.0
Requires-Dist: asn1crypto<2,>=1.0.0
Requires-Dist: pem==23.1.0
Provides-Extra: full
Requires-Dist: frida<18.0.0,>=17.0.0; extra == "full"
Requires-Dist: pyreadline==2.1; sys_platform == "win32"
Dynamic: author
Dynamic: classifier
Dynamic: home-page
Dynamic: provides-extra
Dynamic: requires-dist
Dynamic: requires-python
Dynamic: summary
